libname/__init__.py
libname/fine_calculator.py
libraryfine-0.1.dist-info/LICENSE
libraryfine-0.1.dist-info/METADATA
libraryfine-0.1.dist-info/WHEEL
libraryfine-0.1.dist-info/top_level.txt
libraryfine-0.1.dist-info/RECORD
